versifier/__init__.py
versifier/__main__.py
versifier/compiler.py
versifier/config.py
versifier/core.py
versifier/poetry.py
versifier/stub.py
versifier-0.3.3.dist-info/entry_points.txt
versifier-0.3.3.dist-info/LICENSE
versifier-0.3.3.dist-info/WHEEL
versifier-0.3.3.dist-info/METADATA
versifier-0.3.3.dist-info/RECORD
