Metadata-Version: 2.1
Name: versifier
Version: 0.3.3
Summary: Versifier: A lyrical tool to transform Python requirements into Poetry configurations, effortlessly and elegantly.
Home-page: https://github.com/mrlyc/versifier
Author: MrLYC
Author-email: fx@m.mrlyc.com
Requires-Python: >=3.6.2,<4.0
Classifier: Programming Language :: Python :: 3
Classifier: Programming Language :: Python :: 3.10
Classifier: Programming Language :: Python :: 3.7
Classifier: Programming Language :: Python :: 3.8
Classifier: Programming Language :: Python :: 3.9
Requires-Dist: astunparse (>=1.6.3,<2.0.0)
Requires-Dist: click (==8.0.3)
Requires-Dist: cython (>=3.0.11,<4.0.0)
Requires-Dist: dataclasses (==0.8); python_version < "3.7"
Requires-Dist: pip-requirements-parser (>=32.0.1,<33.0.0)
Requires-Dist: toml (>=0.10.2,<0.11.0)
Project-URL: Documentation, https://mrlyc.github.io/versifier/
Project-URL: Repository, https://github.com/mrlyc/versifier
